topsis_Saurabh_102203677/__init__.py
topsis_Saurabh_102203677/topsis.py
topsis_Saurabh_102203677-1.0.0.dist-info/METADATA
topsis_Saurabh_102203677-1.0.0.dist-info/WHEEL
topsis_Saurabh_102203677-1.0.0.dist-info/entry_points.txt
topsis_Saurabh_102203677-1.0.0.dist-info/top_level.txt
topsis_Saurabh_102203677-1.0.0.dist-info/RECORD
